django_profileboard/__init__.py
django_profileboard/consumers.py
django_profileboard/middleware.py
django_profileboard/models.py
django_profileboard/routing.py
django_profileboard/signals.py
django_profileboard/urls.py
django_profileboard/utils.py
django_profileboard/views.py
django_profileboard/migrations/0001_initial.py
django_profileboard/migrations/0002_alter_databasequery_params_and_more.py
django_profileboard/migrations/__init__.py
django_profileboard/static/profileboard/dashboard.js
django_profileboard/templates/profileboard/dashboard.html
django_profileboard-0.1.1.dist-info/METADATA
django_profileboard-0.1.1.dist-info/WHEEL
django_profileboard-0.1.1.dist-info/licenses/LICENSE
django_profileboard-0.1.1.dist-info/RECORD
