Metadata-Version: 2.4
Name: django-profileboard
Version: 0.1.1
Summary: Production-ready Django performance profiler with live dashboard
Project-URL: Homepage, https://github.com/surendra-ksr/django-profileboard
Project-URL: Repository, https://github.com/surendra-ksr/django-profileboard
Project-URL: Documentation, https://django-profileboard.readthedocs.io
Project-URL: Bug Reports, https://github.com/surendra-ksr/django-profileboard/issues
Author-email: Surendra Reddy Kamini <reddysurendra106@gmail.com>
License-Expression: MIT
License-File: LICENSE
Keywords: dashboard,django,monitoring,performance,profiling
Classifier: Development Status :: 4 - Beta
Classifier: Environment :: Web Environment
Classifier: Framework :: Django
Classifier: Framework :: Django :: 3.2
Classifier: Framework :: Django :: 4.0
Classifier: Framework :: Django :: 4.1
Classifier: Framework :: Django :: 4.2
Classifier: Framework :: Django :: 5.0
Classifier: Intended Audience :: Developers
Classifier: License :: OSI Approved :: MIT License
Classifier: Operating System :: OS Independent
Classifier: Programming Language :: Python
Classifier: Programming Language :: Python :: 3.8
Classifier: Programming Language :: Python :: 3.9
Classifier: Programming Language :: Python :: 3.10
Classifier: Programming Language :: Python :: 3.11
Classifier: Programming Language :: Python :: 3.12
Classifier: Topic :: Internet :: WWW/HTTP
Classifier: Topic :: Software Development :: Debuggers
Classifier: Topic :: System :: Monitoring
Requires-Python: >=3.8
Requires-Dist: channels-redis>=4.0.0
Requires-Dist: channels>=4.0.0
Requires-Dist: django-flags>=5.0.0
Requires-Dist: django>=3.2
Requires-Dist: memray>=1.0.0
Requires-Dist: opentelemetry-instrumentation-django>=0.40b0
